pyfred/__init__.py
pyfred/ex.py
pyfred/fred_client.py
pyfred/__pycache__/__init__.cpython-38.pyc
pyfred/__pycache__/ex.cpython-38.pyc
pyfred/__pycache__/fred_client.cpython-38.pyc
pyfred-0.2.2.dist-info/LICENSE
pyfred-0.2.2.dist-info/METADATA
pyfred-0.2.2.dist-info/WHEEL
pyfred-0.2.2.dist-info/top_level.txt
pyfred-0.2.2.dist-info/RECORD
