Metadata-Version: 2.1
Name: pyfred
Version: 0.2.2
Summary: pyfred
Home-page: UNKNOWN
Author: Jason Darnell
License: MIT
Platform: UNKNOWN
Requires-Dist: requests
Requires-Dist: pandas
Requires-Dist: expiringdict
Provides-Extra: test
Requires-Dist: pytest ; extra == 'test'
Requires-Dist: pytest-cov ; extra == 'test'
